{"3214020001":{"parent":"3214020","bps_code":"3214020001","dagri_code":"32.14.07.2004","text":"TEGALDATAR","postal_codes":["41166"]},"3214020002":{"parent":"3214020","bps_code":"3214020002","dagri_code":"32.14.07.2003","text":"SINARGALIH","postal_codes":["41166"]},"3214020003":{"parent":"3214020","bps_code":"3214020003","dagri_code":"32.14.07.2002","text":"CITAMIANG","postal_codes":["41166"]},"3214020004":{"parent":"3214020","bps_code":"3214020004","dagri_code":"32.14.07.2005","text":"CIJATI","postal_codes":["41166"]},"3214020005":{"parent":"3214020","bps_code":"3214020005","dagri_code":"32.14.07.2001","text":"GUNUNGKARUNG","postal_codes":["41166"]},"3214020006":{"parent":"3214020","bps_code":"3214020006","dagri_code":"32.14.07.2008","text":"PASIRJAMBU","postal_codes":["41166"]},"3214020007":{"parent":"3214020","bps_code":"3214020007","dagri_code":"32.14.07.2006","text":"CIRAMAHILIR","postal_codes":["41166"]},"3214020008":{"parent":"3214020","bps_code":"3214020008","dagri_code":"32.14.07.2007","text":"SUKAMUKTI","postal_codes":["41166"]}}