{"7326160001":{"parent":"7326160","bps_code":"7326160001","dagri_code":"73.26.20.2006","text":"BONTONG MAMULLU","postal_codes":["91835"]},"7326160002":{"parent":"7326160","bps_code":"7326160002","dagri_code":"73.26.20.2005","text":"KAPALA PITU","postal_codes":[]},"7326160003":{"parent":"7326160","bps_code":"7326160003","dagri_code":"73.26.20.2004","text":"KANTUN POYA","postal_codes":["91835"]},"7326160004":{"parent":"7326160","bps_code":"7326160004","dagri_code":"73.26.20.2001","text":"BENTENG KA'DO","postal_codes":[]},"7326160005":{"parent":"7326160","bps_code":"7326160005","dagri_code":"73.26.20.2002","text":"SIKUKU'","postal_codes":["91835"]},"7326160006":{"parent":"7326160","bps_code":"7326160006","dagri_code":"73.26.20.2003","text":"POLO PADANG","postal_codes":["91835"]}}