{"1208040001":{"parent":"1208040","bps_code":"1208040001","dagri_code":"12.09.11.2015","text":"PERBANGUNAN","postal_codes":["21381"]},"1208040002":{"parent":"1208040","bps_code":"1208040002","dagri_code":"12.09.11.2014","text":"PERTAHANAN","postal_codes":["21381"]},"1208040003":{"parent":"1208040","bps_code":"1208040003","dagri_code":"12.09.11.2016","text":"BANGUN BARU","postal_codes":["21381"]},"1208040005":{"parent":"1208040","bps_code":"1208040005","dagri_code":"12.09.11.2011","text":"SEI PAHAM","postal_codes":["21381"]},"1208040006":{"parent":"1208040","bps_code":"1208040006","dagri_code":"12.09.11.2010","text":"SEI KEPAYANG KANAN","postal_codes":["21381"]},"1208040007":{"parent":"1208040","bps_code":"1208040007","dagri_code":"12.09.11.2008","text":"SEI KEPAYANG TENGAH","postal_codes":["21381"]}}