{"1208080001":{"parent":"1208080","bps_code":"1208080001","dagri_code":"12.09.16.2003","text":"LESTARI","postal_codes":["21261"]},"1208080005":{"parent":"1208080","bps_code":"1208080005","dagri_code":"12.09.16.2002","text":"BUNTU PANE","postal_codes":["21261"]},"1208080006":{"parent":"1208080","bps_code":"1208080006","dagri_code":"12.09.16.2001","text":"AMBALUTU","postal_codes":["21261"]},"1208080008":{"parent":"1208080","bps_code":"1208080008","dagri_code":"12.09.16.2005","text":"PRAPAT JANJI","postal_codes":["21261"]},"1208080012":{"parent":"1208080","bps_code":"1208080012","dagri_code":"12.09.16.2007","text":"SEI SILAU TIMUR","postal_codes":["21261"]},"1208080013":{"parent":"1208080","bps_code":"1208080013","dagri_code":"12.09.16.2016","text":"SIONGGANG","postal_codes":["21261"]},"1208080014":{"parent":"1208080","bps_code":"1208080014","dagri_code":"12.09.16.2017","text":"MEKAR SARI","postal_codes":["21261"]},"1208080015":{"parent":"1208080","bps_code":"1208080015","dagri_code":"12.09.16.2018","text":"PERKEBUNAN SEI SILAU","postal_codes":["21261"]},"1208080016":{"parent":"1208080","bps_code":"1208080016","dagri_code":"12.09.16.2019","text":"KARYA AMBALUTU","postal_codes":["21261"]}}