{"3403030001":{"parent":"3403030","bps_code":"3403030001","dagri_code":"34.03.15.2001","text":"KRAMBILSAWIT","postal_codes":["55874"]},"3403030002":{"parent":"3403030","bps_code":"3403030002","dagri_code":"34.03.15.2005","text":"KANIGORO","postal_codes":["55874"]},"3403030003":{"parent":"3403030","bps_code":"3403030003","dagri_code":"34.03.15.2007","text":"PLANJAN","postal_codes":["55874"]},"3403030004":{"parent":"3403030","bps_code":"3403030004","dagri_code":"34.03.15.2006","text":"MONGGOL","postal_codes":["55874"]},"3403030005":{"parent":"3403030","bps_code":"3403030005","dagri_code":"34.03.15.2004","text":"KEPEK","postal_codes":["55874"]},"3403030006":{"parent":"3403030","bps_code":"3403030006","dagri_code":"34.03.15.2002","text":"NGLORO","postal_codes":["55874"]},"3403030007":{"parent":"3403030","bps_code":"3403030007","dagri_code":"34.03.15.2003","text":"JETIS","postal_codes":["55874"]}}