{"3208010":{"parent":"3208","bps_code":"3208010","dagri_code":"32.08.17","text":"DARMA","postal_codes":["45562"]},"3208020":{"parent":"3208","bps_code":"3208020","dagri_code":"32.08.01","text":"KADUGEDE","postal_codes":["45561"]},"3208021":{"parent":"3208","bps_code":"3208021","dagri_code":"32.08.20","text":"NUSAHERANG","postal_codes":["45563"]},"3208030":{"parent":"3208","bps_code":"3208030","dagri_code":"32.08.02","text":"CINIRU","postal_codes":["45565"]},"3208031":{"parent":"3208","bps_code":"3208031","dagri_code":"32.08.26","text":"HANTARA","postal_codes":["45564"]},"3208040":{"parent":"3208","bps_code":"3208040","dagri_code":"32.08.15","text":"SELAJAMBE","postal_codes":["45566"]},"3208050":{"parent":"3208","bps_code":"3208050","dagri_code":"32.08.03","text":"SUBANG","postal_codes":["45586"]},"3208051":{"parent":"3208","bps_code":"3208051","dagri_code":"32.08.25","text":"CILEBAK","postal_codes":["45585"]},"3208060":{"parent":"3208","bps_code":"3208060","dagri_code":"32.08.04","text":"CIWARU","postal_codes":["45583"]},"3208061":{"parent":"3208","bps_code":"3208061","dagri_code":"32.08.29","text":"KARANG KANCANA","postal_codes":["45584"]},"3208070":{"parent":"3208","bps_code":"3208070","dagri_code":"32.08.05","text":"CIBINGBIN","postal_codes":["45587"]},"3208071":{"parent":"3208","bps_code":"3208071","dagri_code":"32.08.28","text":"CIBEUREUM","postal_codes":["45588"]},"3208080":{"parent":"3208","bps_code":"3208080","dagri_code":"32.08.06","text":"LURAGUNG","postal_codes":["45582","45581"]},"3208081":{"parent":"3208","bps_code":"3208081","dagri_code":"32.08.24","text":"CIMAHI","postal_codes":["45582"]},"3208090":{"parent":"3208","bps_code":"3208090","dagri_code":"32.08.11","text":"CIDAHU","postal_codes":["45595","45594"]},"3208091":{"parent":"3208","bps_code":"3208091","dagri_code":"32.08.27","text":"KALIMANGGIS","postal_codes":["45594"]},"3208100":{"parent":"3208","bps_code":"3208100","dagri_code":"32.08.10","text":"CIAWIGEBANG","postal_codes":["45591"]},"3208101":{"parent":"3208","bps_code":"3208101","dagri_code":"32.08.21","text":"CIPICUNG","postal_codes":["45592"]},"3208110":{"parent":"3208","bps_code":"3208110","dagri_code":"32.08.07","text":"LEBAKWANGI","postal_codes":["45571","45574"]},"3208111":{"parent":"3208","bps_code":"3208111","dagri_code":"32.08.30","text":"MALEBER","postal_codes":["45575"]},"3208120":{"parent":"3208","bps_code":"3208120","dagri_code":"32.08.08","text":"GARAWANGI","postal_codes":["45571","45574"]},"3208121":{"parent":"3208","bps_code":"3208121","dagri_code":"32.08.31","text":"SINDANGAGUNG","postal_codes":["45573"]},"3208130":{"parent":"3208","bps_code":"3208130","dagri_code":"32.08.09","text":"KUNINGAN","postal_codes":["45511","45512","45513","45514","45515","45516","45517","45518"]},"3208140":{"parent":"3208","bps_code":"3208140","dagri_code":"32.08.18","text":"CIGUGUR","postal_codes":["45552","45554"]},"3208150":{"parent":"3208","bps_code":"3208150","dagri_code":"32.08.16","text":"KRAMATMULYA","postal_codes":["45556","45553"]},"3208160":{"parent":"3208","bps_code":"3208160","dagri_code":"32.08.12","text":"JALAKSANA","postal_codes":["45552","45554","45553"]},"3208161":{"parent":"3208","bps_code":"3208161","dagri_code":"32.08.23","text":"JAPARA","postal_codes":["45555","45559"]},"3208170":{"parent":"3208","bps_code":"3208170","dagri_code":"32.08.13","text":"CILIMUS","postal_codes":["45556","45553"]},"3208171":{"parent":"3208","bps_code":"3208171","dagri_code":"32.08.32","text":"CIGANDAMEKAR","postal_codes":["45596"]},"3208180":{"parent":"3208","bps_code":"3208180","dagri_code":"32.08.14","text":"MANDIRANCAN","postal_codes":["45558"]},"3208181":{"parent":"3208","bps_code":"3208181","dagri_code":"32.08.22","text":"PANCALANG","postal_codes":["45557"]},"3208190":{"parent":"3208","bps_code":"3208190","dagri_code":"32.08.19","text":"PASAWAHAN","postal_codes":["45555","45559"]}}