{"6308011001":{"parent":"6308011","bps_code":"6308011001","dagri_code":"63.08.09.2001","text":"PAMINGGIR","postal_codes":["71457"]},"6308011002":{"parent":"6308011","bps_code":"6308011002","dagri_code":"63.08.09.2002","text":"PAMINGGIR SEBERANG","postal_codes":["71457"]},"6308011003":{"parent":"6308011","bps_code":"6308011003","dagri_code":"63.08.09.2003","text":"AMBAHAI","postal_codes":["71457"]},"6308011004":{"parent":"6308011","bps_code":"6308011004","dagri_code":"63.08.09.2004","text":"SAPALA","postal_codes":["71457"]},"6308011005":{"parent":"6308011","bps_code":"6308011005","dagri_code":"63.08.09.2005","text":"BARARAWA","postal_codes":["71457"]},"6308011006":{"parent":"6308011","bps_code":"6308011006","dagri_code":"63.08.09.2006","text":"PAL BATU","postal_codes":["71457"]},"6308011007":{"parent":"6308011","bps_code":"6308011007","dagri_code":"63.08.09.2007","text":"TAMPAKANG","postal_codes":["71457"]}}