{"2101011001":{"parent":"2101011","bps_code":"2101011001","dagri_code":"21.02.09.2005","text":"TELAGA TUJUH","postal_codes":["29673"]},"2101011002":{"parent":"2101011","bps_code":"2101011002","dagri_code":"21.02.09.2002","text":"SANGLAR","postal_codes":["29673"]},"2101011003":{"parent":"2101011","bps_code":"2101011003","dagri_code":"21.02.09.2004","text":"SEMEMBANG","postal_codes":["29673"]},"2101011004":{"parent":"2101011","bps_code":"2101011004","dagri_code":"21.02.09.2003","text":"TANJUNG KILANG","postal_codes":["29673"]}}