{"3307031001":{"parent":"3307031","bps_code":"3307031001","dagri_code":"33.07.15.2006","text":"MERGOLANGU","postal_codes":["56375"]},"3307031002":{"parent":"3307031","bps_code":"3307031002","dagri_code":"33.07.15.2003","text":"DEMPEL","postal_codes":["56375"]},"3307031003":{"parent":"3307031","bps_code":"3307031003","dagri_code":"33.07.15.2001","text":"PENGARENGAN","postal_codes":["56375"]},"3307031004":{"parent":"3307031","bps_code":"3307031004","dagri_code":"33.07.15.2002","text":"KALIKARUNG","postal_codes":["56375"]},"3307031005":{"parent":"3307031","bps_code":"3307031005","dagri_code":"33.07.15.2004","text":"KARANGSAMBUNG","postal_codes":["56375"]},"3307031006":{"parent":"3307031","bps_code":"3307031006","dagri_code":"33.07.15.2007","text":"DEPOK","postal_codes":["56375"]},"3307031007":{"parent":"3307031","bps_code":"3307031007","dagri_code":"33.07.15.2008","text":"KALIALANG","postal_codes":["56375"]},"3307031008":{"parent":"3307031","bps_code":"3307031008","dagri_code":"33.07.15.2005","text":"TEMPUREJO","postal_codes":["56375"]}}