{"1210061001":{"parent":"1210061","bps_code":"1210061001","dagri_code":"12.11.11.2001","text":"SUMBUL","postal_codes":["22264"]},"1210061002":{"parent":"1210061","bps_code":"1210061002","dagri_code":"12.11.11.2002","text":"KENTARA","postal_codes":["22264"]},"1210061003":{"parent":"1210061","bps_code":"1210061003","dagri_code":"12.11.11.2003","text":"LAE PARIRA","postal_codes":["22264"]},"1210061004":{"parent":"1210061","bps_code":"1210061004","dagri_code":"12.11.11.2004","text":"BULUDURI","postal_codes":["22264"]},"1210061005":{"parent":"1210061","bps_code":"1210061005","dagri_code":"12.11.11.2005","text":"SEMPUNG POLLING","postal_codes":["22264"]},"1210061006":{"parent":"1210061","bps_code":"1210061006","dagri_code":"12.11.11.2008","text":"PANDIANGAN","postal_codes":["22264"]},"1210061007":{"parent":"1210061","bps_code":"1210061007","dagri_code":"12.11.11.2006","text":"LUMBAN SIHITE","postal_codes":["22264"]},"1210061008":{"parent":"1210061","bps_code":"1210061008","dagri_code":"12.11.11.2007","text":"LUMBAN TORUAN","postal_codes":["22264"]},"1210061009":{"parent":"1210061","bps_code":"1210061009","dagri_code":"12.11.11.2009","text":"KABAN JULU","postal_codes":[]}}