{"1404011001":{"parent":"1404011","bps_code":"1404011001","dagri_code":"14.05.02.2005","text":"RANTAU BARU","postal_codes":["28317"]},"1404011002":{"parent":"1404011","bps_code":"1404011002","dagri_code":"14.05.02.2002","text":"KUALA TERUSAN","postal_codes":["28316"]},"1404011003":{"parent":"1404011","bps_code":"1404011003","dagri_code":"14.05.02.1008","text":"PANGKALAN KERINCI KOTA","postal_codes":["28311"]},"1404011005":{"parent":"1404011","bps_code":"1404011005","dagri_code":"14.05.02.2001","text":"MEKAR JAYA","postal_codes":[]},"1404011006":{"parent":"1404011","bps_code":"1404011006","dagri_code":"14.05.02.2003","text":"MAKMUR","postal_codes":["28314"]},"1404011007":{"parent":"1404011","bps_code":"1404011007","dagri_code":"14.05.02.1007","text":"PANGKALAN KERINCI BARAT","postal_codes":["28313"]},"1404011008":{"parent":"1404011","bps_code":"1404011008","dagri_code":"14.05.02.1009","text":"PANGKALAN KERINCI TIMUR","postal_codes":["28312"]}}