{"6212010":{"parent":"6212","bps_code":"6212010","dagri_code":"62.13.02","text":"BANUA LIMA","postal_codes":["73661"]},"6212020":{"parent":"6212","bps_code":"6212020","dagri_code":"62.13.01","text":"DUSUN TIMUR","postal_codes":["73611","73612","73613","73614","73615","73616","73617","73619"]},"6212021":{"parent":"6212","bps_code":"6212021","dagri_code":"62.13.07","text":"PAJU EPAT","postal_codes":["73651"]},"6212030":{"parent":"6212","bps_code":"6212030","dagri_code":"62.13.04","text":"AWANG","postal_codes":["73681"]},"6212040":{"parent":"6212","bps_code":"6212040","dagri_code":"62.13.03","text":"PATANGKEP TUTUI","postal_codes":["73671"]},"6212050":{"parent":"6212","bps_code":"6212050","dagri_code":"62.13.05","text":"DUSUN TENGAH","postal_codes":["73652"]},"6212051":{"parent":"6212","bps_code":"6212051","dagri_code":"62.13.08","text":"RAREN BATUAH","postal_codes":["73654"]},"6212052":{"parent":"6212","bps_code":"6212052","dagri_code":"62.13.09","text":"PAKU","postal_codes":["73656"]},"6212053":{"parent":"6212","bps_code":"6212053","dagri_code":"62.13.10","text":"KARUSEN JANANG","postal_codes":["73655"]},"6212060":{"parent":"6212","bps_code":"6212060","dagri_code":"62.13.06","text":"PEMATANG KARAU","postal_codes":["73653"]}}