{"1871010005":{"parent":"1871010","bps_code":"1871010005","dagri_code":"18.71.08.1005","text":"BAKUNG","postal_codes":["35232"]},"1871010006":{"parent":"1871010","bps_code":"1871010006","dagri_code":"18.71.08.1006","text":"KURIPAN","postal_codes":["35232"]},"1871010007":{"parent":"1871010","bps_code":"1871010007","dagri_code":"18.71.08.1007","text":"NEGERI OLOK GADING","postal_codes":["35233"]},"1871010008":{"parent":"1871010","bps_code":"1871010008","dagri_code":"18.71.08.1008","text":"SUKARAME II","postal_codes":["35234"]},"1871010011":{"parent":"1871010","bps_code":"1871010011","dagri_code":"18.71.08.1009","text":"BATU PUTUK","postal_codes":[]}}