{"1377010":{"parent":"1377","bps_code":"1377010","dagri_code":"13.77.03","text":"PARIAMAN SELATAN","postal_codes":[]},"1377020":{"parent":"1377","bps_code":"1377020","dagri_code":"13.77.01","text":"PARIAMAN TENGAH","postal_codes":["25511","25512","25513","25514","25515","25516","25517","25518","25519"]},"1377021":{"parent":"1377","bps_code":"1377021","dagri_code":"13.77.04","text":"PARIAMAN TIMUR","postal_codes":["25546","25549"]},"1377030":{"parent":"1377","bps_code":"1377030","dagri_code":"13.77.02","text":"PARIAMAN UTARA","postal_codes":[]}}