{"9430015001":{"parent":"9430015","bps_code":"9430015001","dagri_code":"91.23.30.2003","text":"JIWIKELANNY","postal_codes":[]},"9430015002":{"parent":"9430015","bps_code":"9430015002","dagri_code":"91.23.30.2004","text":"NISIMOK","postal_codes":[]},"9430015003":{"parent":"9430015","bps_code":"9430015003","dagri_code":"91.23.30.2005","text":"YUGUME","postal_codes":[]},"9430015004":{"parent":"9430015","bps_code":"9430015004","dagri_code":"91.23.30.2001","text":"INDUGU","postal_codes":[]},"9430015005":{"parent":"9430015","bps_code":"9430015005","dagri_code":"91.23.30.2002","text":"GUBURINI","postal_codes":[]},"9430015006":{"parent":"9430015","bps_code":"9430015006","dagri_code":"91.23.30.2006","text":"PINAME","postal_codes":[]},"9430015007":{"parent":"9430015","bps_code":"9430015007","dagri_code":"91.23.30.2007","text":"LONDU","postal_codes":[]},"9430015008":{"parent":"9430015","bps_code":"9430015008","dagri_code":"91.23.30.2008","text":"KAGALUWI","postal_codes":[]}}