{"9101084001":{"parent":"9101084","bps_code":"9101084001","dagri_code":"92.03.13.2001","text":"ANDAMATA","postal_codes":[]},"9101084002":{"parent":"9101084","bps_code":"9101084002","dagri_code":"92.03.13.2003","text":"ARGUNI","postal_codes":[]},"9101084003":{"parent":"9101084","bps_code":"9101084003","dagri_code":"92.03.13.2004","text":"FIOR","postal_codes":[]},"9101084004":{"parent":"9101084","bps_code":"9101084004","dagri_code":"92.03.13.2005","text":"FURIR","postal_codes":[]},"9101084005":{"parent":"9101084","bps_code":"9101084005","dagri_code":"92.03.13.2002","text":"TAVER","postal_codes":[]}}