{"9104040001":{"parent":"9104040","bps_code":"9104040001","dagri_code":"92.06.07.2001","text":"WAMESA I / IDOOR","postal_codes":["98577"]},"9104040002":{"parent":"9104040","bps_code":"9104040002","dagri_code":"92.06.07.2003","text":"YANSEI","postal_codes":[]},"9104040003":{"parent":"9104040","bps_code":"9104040003","dagri_code":"92.06.07.2002","text":"WAMESA II / YAKATI","postal_codes":["98577"]},"9104040004":{"parent":"9104040","bps_code":"9104040004","dagri_code":"92.06.07.2004","text":"MAMURANU","postal_codes":["98577"]}}