{"3522051001":{"parent":"3522051","bps_code":"3522051001","dagri_code":"35.22.26.2001","text":"KRONDONAN","postal_codes":["62173"]},"3522051002":{"parent":"3522051","bps_code":"3522051002","dagri_code":"35.22.26.2003","text":"SAMBONGREJO","postal_codes":["62173"]},"3522051003":{"parent":"3522051","bps_code":"3522051003","dagri_code":"35.22.26.2004","text":"PAJENG","postal_codes":["62173"]},"3522051004":{"parent":"3522051","bps_code":"3522051004","dagri_code":"35.22.26.2005","text":"GONDANG","postal_codes":["62173"]},"3522051005":{"parent":"3522051","bps_code":"3522051005","dagri_code":"35.22.26.2002","text":"JARI","postal_codes":["62173"]},"3522051006":{"parent":"3522051","bps_code":"3522051006","dagri_code":"35.22.26.2006","text":"SENGANTEN","postal_codes":["62173"]},"3522051007":{"parent":"3522051","bps_code":"3522051007","dagri_code":"35.22.26.2007","text":"PRAGELAN","postal_codes":["62173"]}}