{"5310041001":{"parent":"5310041","bps_code":"5310041001","dagri_code":"53.07.09.2003","text":"POGON","postal_codes":["86182"]},"5310041002":{"parent":"5310041","bps_code":"5310041002","dagri_code":"53.07.09.2004","text":"AIBURA","postal_codes":["86182"]},"5310041003":{"parent":"5310041","bps_code":"5310041003","dagri_code":"53.07.09.2005","text":"WAIRBLELER","postal_codes":["86182"]},"5310041004":{"parent":"5310041","bps_code":"5310041004","dagri_code":"53.07.09.2006","text":"HODER","postal_codes":["86182"]},"5310041005":{"parent":"5310041","bps_code":"5310041005","dagri_code":"53.07.09.2002","text":"EGON","postal_codes":["86182"]},"5310041006":{"parent":"5310041","bps_code":"5310041006","dagri_code":"53.07.09.2008","text":"NANGATOBONG","postal_codes":["86182"]},"5310041007":{"parent":"5310041","bps_code":"5310041007","dagri_code":"53.07.09.2007","text":"WAIRTERANG","postal_codes":["86182"]},"5310041008":{"parent":"5310041","bps_code":"5310041008","dagri_code":"53.07.09.2009","text":"WATUDIRAN","postal_codes":["86182"]},"5310041009":{"parent":"5310041","bps_code":"5310041009","dagri_code":"53.07.09.2001","text":"RUNUT","postal_codes":["86182"]}}