{"1601093001":{"parent":"1601093","bps_code":"1601093001","dagri_code":"16.01.32.2001","text":"BUNGLAI","postal_codes":[]},"1601093002":{"parent":"1601093","bps_code":"1601093002","dagri_code":"16.01.32.2002","text":"KEDATON","postal_codes":[]},"1601093003":{"parent":"1601093","bps_code":"1601093003","dagri_code":"16.01.32.2003","text":"KAMPAI","postal_codes":[]},"1601093004":{"parent":"1601093","bps_code":"1601093004","dagri_code":"16.01.32.2004","text":"RANTAU PANJANG","postal_codes":[]},"1601093005":{"parent":"1601093","bps_code":"1601093005","dagri_code":"16.01.32.2006","text":"SUKA PINDAH","postal_codes":[]},"1601093006":{"parent":"1601093","bps_code":"1601093006","dagri_code":"16.01.32.2008","text":"LUBUK KEMILING","postal_codes":[]},"1601093007":{"parent":"1601093","bps_code":"1601093007","dagri_code":"16.01.32.2007","text":"SINAR KEDATON","postal_codes":[]},"1601093008":{"parent":"1601093","bps_code":"1601093008","dagri_code":"16.01.32.2005","text":"KEDATON TIMUR","postal_codes":[]}}