{"1601083001":{"parent":"1601083","bps_code":"1601083001","dagri_code":"16.01.31.2001","text":"KEMALA JAYA","postal_codes":["32159"]},"1601083002":{"parent":"1601083","bps_code":"1601083002","dagri_code":"16.01.31.2002","text":"LONTAR","postal_codes":["32159"]},"1601083003":{"parent":"1601083","bps_code":"1601083003","dagri_code":"16.01.31.2004","text":"LUBUK TUPAK","postal_codes":["32159"]},"1601083004":{"parent":"1601083","bps_code":"1601083004","dagri_code":"16.01.31.2005","text":"BERINGIN","postal_codes":["32159"]},"1601083005":{"parent":"1601083","bps_code":"1601083005","dagri_code":"16.01.31.2003","text":"MUARA SAEH","postal_codes":["32159"]},"1601083006":{"parent":"1601083","bps_code":"1601083006","dagri_code":"16.01.31.2006","text":"SURAU","postal_codes":["32159"]},"1601083007":{"parent":"1601083","bps_code":"1601083007","dagri_code":"16.01.31.2007","text":"KARANG LANTANG","postal_codes":["32159"]}}