{"2102051001":{"parent":"2102051","bps_code":"2102051001","dagri_code":"21.01.10.2005","text":"SEBONG PEREH","postal_codes":["29155"]},"2102051002":{"parent":"2102051","bps_code":"2102051002","dagri_code":"21.01.10.2004","text":"SEBONG LAGOI","postal_codes":["29155"]},"2102051003":{"parent":"2102051","bps_code":"2102051003","dagri_code":"21.01.10.2002","text":"EKANG ANCULAI","postal_codes":["29155"]},"2102051004":{"parent":"2102051","bps_code":"2102051004","dagri_code":"21.01.10.2006","text":"SRI BINTAN","postal_codes":["29155"]},"2102051005":{"parent":"2102051","bps_code":"2102051005","dagri_code":"21.01.10.2003","text":"PENGUDANG","postal_codes":["29155"]},"2102051006":{"parent":"2102051","bps_code":"2102051006","dagri_code":"21.01.10.2001","text":"BERAKIT","postal_codes":["29155"]},"2102051007":{"parent":"2102051","bps_code":"2102051007","dagri_code":"21.01.10.1007","text":"KOTA BARU","postal_codes":["29155"]}}